MANIFEST.in
README.rst
helga_mimic.py
setup.py
helga_mimic.egg-info/PKG-INFO
helga_mimic.egg-info/SOURCES.txt
helga_mimic.egg-info/dependency_links.txt
helga_mimic.egg-info/entry_points.txt
helga_mimic.egg-info/requires.txt
helga_mimic.egg-info/top_level.txt
helga_mimic.egg-info/zip-safe