Metadata-Version: 1.1
Name: helga-mimic
Version: 0.4.10
Summary: mimics users or channels
Home-page: UNKNOWN
Author: Justin Caratzas
Author-email: bigjust@lambdaphil.es
License: LICENSE
Keywords: irc bot mimic
Platform: UNKNOWN
Classifier: Development Status :: 3 - Alpha
Classifier: License :: OSI Approved :: GNU General Public License v3 (GPLv3)
Classifier: Operating System :: OS Independent
Classifier: Programming Language :: Python
Classifier: Topic :: Software Development :: Libraries :: Python Modules
